cognipy/__init__.py
cognipy/interop.py
cognipy/ontology.py
cognipy/CogniPyCLI/bin/Release/CogniPyCLI.exe
cognipy/CogniPyCLI/bin/Release/CogniPyCLI.exe.config
cognipy/CogniPyCLI/bin/Release/CogniPyCLI.pdb
cognipy/CogniPyCLI/bin/Release/CogniPyLib.dll
cognipy/CogniPyCLI/bin/Release/CogniPyLib.dll.config
cognipy/CogniPyCLI/bin/Release/CogniPyLib.pdb
cognipy/CogniPyCLI/bin/Release/IKVM.AWT.WinForms.dll
cognipy/CogniPyCLI/bin/Release/IKVM.OpenJDK.Beans.dll
cognipy/CogniPyCLI/bin/Release/IKVM.OpenJDK.Charsets.dll
cognipy/CogniPyCLI/bin/Release/IKVM.OpenJDK.Corba.dll
cognipy/CogniPyCLI/bin/Release/IKVM.OpenJDK.Core.dll
cognipy/CogniPyCLI/bin/Release/IKVM.OpenJDK.Jdbc.dll
cognipy/CogniPyCLI/bin/Release/IKVM.OpenJDK.Management.dll
cognipy/CogniPyCLI/bin/Release/IKVM.OpenJDK.Media.dll
cognipy/CogniPyCLI/bin/Release/IKVM.OpenJDK.Misc.dll
cognipy/CogniPyCLI/bin/Release/IKVM.OpenJDK.Naming.dll
cognipy/CogniPyCLI/bin/Release/IKVM.OpenJDK.Remoting.dll
cognipy/CogniPyCLI/bin/Release/IKVM.OpenJDK.Security.dll
cognipy/CogniPyCLI/bin/Release/IKVM.OpenJDK.SwingAWT.dll
cognipy/CogniPyCLI/bin/Release/IKVM.OpenJDK.Text.dll
cognipy/CogniPyCLI/bin/Release/IKVM.OpenJDK.Util.dll
cognipy/CogniPyCLI/bin/Release/IKVM.OpenJDK.XML.API.dll
cognipy/CogniPyCLI/bin/Release/IKVM.OpenJDK.XML.Parse.dll
cognipy/CogniPyCLI/bin/Release/IKVM.Runtime.JNI.dll
cognipy/CogniPyCLI/bin/Release/IKVM.Runtime.dll
cognipy/CogniPyCLI/bin/Release/NMemory.dll
cognipy/CogniPyCLI/bin/Release/NMemory.xml
cognipy/CogniPyCLI/bin/Release/Newtonsoft.Json.dll
cognipy/CogniPyCLI/bin/Release/Newtonsoft.Json.xml
cognipy/CogniPyCLI/bin/Release/elk.dll
cognipy/CogniPyCLI/bin/Release/hermit.dll
cognipy/CogniPyCLI/bin/Release/jena.dll
cognipy/CogniPyCLI/bin/Release/owlapi.dll
cognipy-1.0.21.dist-info/LICENSE
cognipy-1.0.21.dist-info/METADATA
cognipy-1.0.21.dist-info/WHEEL
cognipy-1.0.21.dist-info/top_level.txt
cognipy-1.0.21.dist-info/RECORD
