Metadata-Version: 2.2
Name: cognipy
Version: 1.0.21
Summary: CogniPy for Pandas, Semantic Tech Reasoner and Editor
Home-page: https://github.com/cognitum-octopus/cognipy
Author: Cognitum Services S.A.
Author-email: support@cognitum.eu
Classifier: Development Status :: 3 - Alpha
Classifier: Intended Audience :: Developers
Classifier: License :: OSI Approved :: Apache Software License
Classifier: Programming Language :: C#
Classifier: Programming Language :: Python :: 3
Classifier: Programming Language :: Python :: 3.5
Classifier: Programming Language :: Python :: 3.6
Classifier: Programming Language :: Python :: 3.7
Classifier: Operating System :: Microsoft :: Windows
Classifier: Operating System :: POSIX :: Linux
Classifier: Operating System :: MacOS :: MacOS X
License-File: LICENSE
Requires-Dist: pandas
Requires-Dist: pydot
Requires-Dist: ipywidgets
Requires-Dist: graphviz
Dynamic: author
Dynamic: author-email
Dynamic: classifier
Dynamic: description
Dynamic: description-content-type
Dynamic: home-page
Dynamic: requires-dist
Dynamic: summary
